tl_mcp_server/taolve/__init__.py
tl_mcp_server/taolve/main.py
tl_mcp_server-0.1.8.dist-info/METADATA
tl_mcp_server-0.1.8.dist-info/WHEEL
tl_mcp_server-0.1.8.dist-info/entry_points.txt
tl_mcp_server-0.1.8.dist-info/top_level.txt
tl_mcp_server-0.1.8.dist-info/RECORD
